{
  "dontcare": [],
  "valid_line": [
  {
      "words": [
        {
          "quad": {
              "x4": 646,
              "x2": 27,
              "x1": 1020,
              "y1": 27,
              "y2": 1020,
              "y3": 208,
              "x3": 646,
              "y4": 208
          },
          "text": "&“~ EUROCORPORATION CONSULENZA E GESTIONE RIFLUTL"
        }
      ],
      "category": "header"
    },
	
	  {
      "words": [
        {
          "quad": {
              "x4": 291,
              "x2": 284,
              "x1": 610,
              "y1": 284,
              "y2": 610,
              "y3": 347,
              "x3": 291,
              "y4": 347
          },
          "text": "PER AUTISTA"
        }
      ],
      "category": "other"
    },
	
		  {
      "words": [
        {
          "quad": {
              "x4": 1078,
              "x2": 282,
              "x1": 1383,
              "y1": 282,
              "y2": 1383,
              "y3": 345,
              "x3": 1078,
              "y4": 345
          },
          "text": "PER UFFICIO"
        }
      ],
      "category": "other"
    },
     {
      "words": [
        {
          "quad": {
              "x4": 59,
              "x2": 369,
              "x1": 239,
              "y1": 369,
              "y2": 236,
              "y3": 401,
              "x3": 59,
              "y4": 401
          },
          "text": "PRODUTTORE"
        }
      ],
      "category": "question"
    },
    {
      "words": [
        {
          "quad": {
              "x4": 270,
              "x2": 371,
              "x1": 512,
              "y1": 371,
              "y2": 512,
              "y3": 402,
              "x3": 270,
              "y4": 402
          },
          "text": "D&D Costruzioni SRL"
        }
      ],
      "category": "answer"
    },
	
	    {
      "words": [
        {
          "quad": {
              "x4": 854,
              "x2": 361,
              "x1": 979,
              "y1": 361,
              "y2": 979,
              "y3": 406,
              "x3": 854,
              "y4": 406
          },
          "text": "CLIENTE"
        }
      ],
      "category": "question"
    },
	{
	      "words": [
        {
          "quad": {
              "x4": 1082,
              "x2": 371,
              "x1": 1331,
              "y1": 371,
              "y2": 1331,
              "y3": 403,
              "x3": 1082,
              "y4": 403
          },
          "text": "D&D Costruzioni SRL"
        }
      ],
      "category": "answer"
    },
		    {
      "words": [
        {
          "quad": {
              "x4": 851,
              "x2": 439,
              "x1": 1000,
              "y1": 439,
              "y2": 1000,
              "y3": 493,
              "x3": 851,
              "y4": 493
          },
          "text": "Operatore"
        }
      ],
      "category": "question"
    },
	
	{
	"words": [
        {
          "quad": {
              "x4": 1084,
              "x2": 452,
              "x1": 1471,
              "y1": 452,
              "y2": 1471,
              "y3": 491,
              "x3": 1084,
              "y4": 491
          },
          "text": "Mario Nobile - Mob. 3381558401"
        }
      ],
      "category": "answer"
    },
			    {
      "words": [
        {
          "quad": {
              "x4": 857,
              "x2": 532,
              "x1": 1033,
              "y1": 532,
              "y2": 1033,
              "y3": 568,
              "x3": 857,
              "y4": 568
          },
          "text": "CF Produttore"
        }
      ],
      "category": "question"
    },
	{
		"words": [
        {
          "quad": {
              "x4": 1082,
              "x2": 534,
              "x1": 1250,
              "y1": 534,
              "y2": 1250,
              "y3": 570,
              "x3": 1082,
              "y4": 570
          },
          "text": "06725110487"
        }
      ],
      "category": "answer"
    },
				    {
      "words": [
        {
          "quad": {
              "x4": 851,
              "x2": 582,
              "x1": 1030,
              "y1": 582,
              "y2": 1030,
              "y3": 624,
              "x3": 851,
              "y4": 624
          },
          "text": "Email Cliente"
        }
      ],
      "category": "question"
    },
	{
			"words": [
        {
          "quad": {
              "x4": 1082,
              "x2": 588,
              "x1": 1365,
              "y1": 588,
              "y2": 1365,
              "y3": 622,
              "x3": 1082,
              "y4": 622
          },
          "text": "info@ddcostruzioni.net"
        }
      ],
      "category": "answer"
    },
					    {
      "words": [
        {
          "quad": {
              "x4": 851,
              "x2": 636,
              "x1": 1066,
              "y1": 636,
              "y2": 1066,
              "y3": 678,
              "x3": 851,
              "y4": 678
          },
          "text": "Email Produttore"
        }
      ],
      "category": "question"
    },
	{
	"words": [
        {
          "quad": {
              "x4": 1082,
              "x2": 640,
              "x1": 1365,
              "y1": 640,
              "y2": 1365,
              "y3": 676,
              "x3": 1080,
              "y4": 676
          },
          "text": "info@ddcostruzioni.net"
        }
      ],
      "category": "answer"
    },
	
	{
      "words": [
        {
          "quad": {
              "x4": 361,
              "x2": 690,
              "x1": 549,
              "y1": 690,
              "y2": 549,
              "y3": 753,
              "x3": 361,
              "y4": 753
          },
          "text": "ORARI"
        }
      ],
      "category": "other"
    },
	
     {
      "words": [
        {
          "quad": {
              "x4": 57,
              "x2": 448,
              "x1": 190,
              "y1": 448,
              "y2": 190,
              "y3": 489,
              "x3": 57,
              "y4": 489
          },
          "text": "UnitLoc."
        }
      ],
      "category": "question"
    },	
  {
      "words": [
        {
          "quad": {
              "x4": 270,
              "x2": 453,
              "x1": 836,
              "y1": 453,
              "y2": 836,
              "y3": 489,
              "x3": 270,
              "y4": 489
          },
          "text": "PORTA ROMANA - VIA METASTASIO 48 50124 (FI)"
        }
      ],
      "category": "answer"
    },	
	
	  {
      "words": [
        {
          "quad": {
              "x4": 57,
              "x2": 529,
              "x1": 200,
              "y1": 529,
              "y2": 200,
              "y3": 571,
              "x3": 57,
              "y4": 571
          },
          "text": "Referente"
        }
      ],
      "category": "question"
    },
	
		  {
      "words": [
        {
          "quad": {
              "x4": 263,
              "x2": 532,
              "x1": 473,
              "y1": 532,
              "y2": 473,
              "y3": 570,
              "x3": 263,
              "y4": 570
          },
          "text": "FABRIZIO PIPOLO"
        }
      ],
      "category": "answer"
    },
		  {
      "words": [
        {
          "quad": {
              "x4": 57,
              "x2": 585,
              "x1": 200,
              "y1": 585,
              "y2": 200,
              "y3": 621,
              "x3": 57,
              "y4": 621
          },
          "text": "Telefono"
        }
      ],
      "category": "question"
    },


		  {
      "words": [
        {
          "quad": {
              "x4": 263,
              "x2": 586,
              "x1": 428,
              "y1": 586,
              "y2": 428,
              "y3": 620,
              "x3": 263,
              "y4": 620
          },
          "text": "3357566640"
        }
      ],
      "category": "answer"
    },
	{
      "words": [
        {
          "quad": {
              "x4": 59,
              "x2": 640,
              "x1": 240,
              "y1": 640,
              "y2": 240,
              "y3": 676,
              "x3": 59,
              "y4": 676
          },
          "text": "Data Richiesta"
        }
      ],
      "category": "question"
    },	
  {
      "words": [
        {
          "quad": {
              "x4": 277,
              "x2": 643,
              "x1": 436,
              "y1": 643,
              "y2": 436,
              "y3": 673,
              "x3": 277,
              "y4": 673
          },
          "text": "23/02/2022"
        }
      ],
      "category": "answer"
    },	
	
	
  {
      "words": [
        {
          "quad": {
              "x4": 459,
              "x2": 636,
              "x1": 654,
              "y1": 636,
              "y2": 654,
              "y3": 677,
              "x3": 459,
              "y4": 677
          },
          "text": "orario richiesta"
        }
      ],
      "category": "question"
    },
	
  {
      "words": [
        {
          "quad": {
              "x4": 711,
              "x2": 640,
              "x1": 794,
              "y1": 640,
              "y2": 794,
              "y3": 674,
              "x3": 711,
              "y4": 674
          },
          "text": "08:00"
        }
      ],
      "category": "answer"
    },
	
	
	  {
      "words": [
        {
          "quad": {
              "x4": 61,
              "x2": 758,
              "x1": 170,
              "y1": 758,
              "y2": 170,
              "y3": 799,
              "x3": 61,
              "y4": 799
          },
          "text": "Mattina"
        }
      ],
      "category": "question"
    },	
	
	
		  {
      "words": [
        {
          "quad": {
              "x4": 224,
              "x2": 756,
              "x1": 805,
              "y1": 756,
              "y2": 805,
              "y3": 797,
              "x3": 224,
              "y4": 797
          },
          "text": "Dalle 08:00 Alle 12:00"
        }
      ],
      "category": "answer"
    },


		  {
      "words": [
        {
          "quad": {
              "x4": 61,
              "x2": 815,
              "x1": 201,
              "y1": 815,
              "y2": 201,
              "y3": 849,
              "x3": 61,
              "y4": 849
          },
          "text": "Pomeriggio"
        }
      ],
      "category": "question"
    },		
	
			  {
      "words": [
        {
          "quad": {
              "x4": 222,
              "x2": 812,
              "x1": 808,
              "y1": 812,
              "y2": 808,
              "y3": 850,
              "x3": 222,
              "y4": 850
          },
          "text": "Dalle Alle"
        }
      ],
      "category": "answer"
    },	

			  {
      "words": [
        {
          "quad": {
              "x4": 247,
              "x2": 862,
              "x1": 645,
              "y1": 862,
              "y2": 645,
              "y3": 916,
              "x3": 247,
              "y4": 916
          },
          "text": "VEICOLO RICHIESTO"
        }
      ],
      "category": "other"
    },	
	
				  {
      "words": [
        {
          "quad": {
              "x4": 710,
              "x2": 1283,
              "x1": 954,
              "y1": 1283,
              "y2": 954,
              "y3": 1321,
              "x3": 710,
              "y4": 1321
          },
          "text": "Tipologia rifiuto"
        }
      ],
      "category": "other"
    },	
	
					  {
      "words": [
        {
          "quad": {
              "x4": 113,
              "x2": 1349,
              "x1": 181,
              "y1": 1349,
              "y2": 181,
              "y3": 1397,
              "x3": 113,
              "y4": 1397
          },
          "text": "CER"
        }
      ],
      "category": "question"
    },	
	
  {
      "words": [
        {
          "quad": {
              "x4": 92,
              "x2": 1447,
              "x1": 205,
              "y1": 1447,
              "y2": 205,
              "y3": 1483,
              "x3": 92,
              "y4": 1483
          },
          "text": "170904.1"
        }
      ],
      "category": "answer"
    },
	
  {
      "words": [
        {
          "quad": {
              "x4": 851,
              "x2": 758,
              "x1": 1165,
              "y1": 758,
              "y2": 1165,
              "y3": 805,
              "x3": 851,
              "y4": 805
          },
          "text": "PER LA LOGISTICA"
        }
      ],
      "category": "question"
    },	
  {
      "words": [
        {
          "quad": {
              "x4": 853,
              "x2": 810,
              "x1": 1617,
              "y1": 810,
              "y2": 1617,
              "y3": 1218,
              "x3": 853,
              "y4": 1218
          },
          "text": "SCHEDA FATTA DA MATILDE CHIAMARE PER COMUNICARE ORARIO Florec 3200436592 PORTARE A CAMBIO N.5 CASSE VENERDì MATTINA 25.02.2022https://www.google.com/maps/@43.7602578,11.2378078,3a,75y,244.78h,76.14t/data=!3m7!1e1!3m5! 1sd6ERXwcpkiHcDdpt_LkqMA!2e0!6shttps:%2F%  2Fstreetviewpixels-pa.googleapis.com%2Fv1%2Fthumbnail% 3Fpanoid%3Dd6ERXwcpkiHcDdpt_LkqMA%26cb_client% 3Dmaps_sv.tactile.gps%26w%3D203%26h%3D100%26yaw% 3D322.34424%26pitch%3D0%26thumbfov%3D100!7i16384! 8i8192"
        }
      ],
      "category": "answer"
    },	
	
    {
      "words": [
        {
          "quad": {
              "x4": 383,
              "x2": 2188,
              "x1": 1283,
              "y1": 2188,
              "y2": 1283,
              "y3": 2288,
              "x3": 383,
              "y4": 2288
          },
          "text": "EUROCORPORATION S.r.l. C.F. - P.iva 05235640488 R.E.A. 531452 Capitale Sociale € 100.000,000 Via de’ Cattani 178 - 50145 Firenze | Tel. 055 7222419 Fax 055 7227520 info@eurocorporation.it | info@pec.eurocorporation.it | www.eurocorporation.it"
        }
      ],
      "category": "header"
    },	
	
	
	  {
      "words": [
        {
          "quad": {
              "x4": 91,
              "x2": 2283,
              "x1": 231,
              "y1": 2283,
              "y2": 231,
              "y3": 2322,
              "x3": 91,
              "y4": 2322
          },
          "text": "Pag. 1 di 2"
        }
      ],
      "category": "other"
    },	
	
		  {
      "words": [
        {
          "quad": {
              "x4": 1408,
              "x2": 2283,
              "x1": 1546,
              "y1": 2283,
              "y2": 1546,
              "y3": 2324,
              "x3": 1408,
              "y4": 2324
          },
          "text": "15/02/2022"
        }
      ],
      "category": "other"
    }	
	
  ],
  "meta": {
	 "version": "v0.1",
    "split": "train",
	"image_id": 1,
    "image_size": {
      "width": 1653,
      "height": 2339
       }
    },
    "roi": {
    },
    "repeating_symbol": [
    ]
}